Metadata-Version: 2.1
Name: deepsphere
Version: 0.2.1
Summary: Deep Sphere package
Home-page: UNKNOWN
Author: Arcanite
Author-email: contact@arcanite.ch
License: UNKNOWN
Platform: UNKNOWN
Provides-Extra: tests
